{
  "formatVersion": "1.1",
  "component": {
    "group": "ninja.bytecode.shuriken",
    "module": "shuriken-core",
    "version": "2.0.3",
    "attributes": {
      "org.gradle.status": "release"
    }
  },
  "createdBy": {
    "gradle": {
      "version": "6.3",
      "buildId": "6nai2qmdwvhy3pjach4k6i6k2m"
    }
  },
  "variants": [
    {
      "name": "apiElements",
      "attributes": {
        "org.gradle.category": "library",
        "org.gradle.dependency.bundling": "external",
        "org.gradle.jvm.version": 8,
        "org.gradle.libraryelements": "jar",
        "org.gradle.usage": "java-api"
      },
      "files": [
        {
          "name": "shuriken-core-2.0.3.jar",
          "url": "shuriken-core-2.0.3.jar",
          "size": 288848,
          "sha512": "bcdca4ef37ab4e86b8c6da35382461b9f0ad57e2873af0515773398239728c5f80a877411e59f502cd56a42c4bc549fd4ef2fd2e1ad36a0f414cbe586f000379",
          "sha256": "5ab64e8d729e3a3f58d0ad6563913bf16ab677e81ff611722c1f6803d230a108",
          "sha1": "f536b337db5cb8a03e186726fc36b1245fec8eca",
          "md5": "d0d01715196b62e2e3efdabad2a1d1d1"
        }
      ]
    },
    {
      "name": "runtimeElements",
      "attributes": {
        "org.gradle.category": "library",
        "org.gradle.dependency.bundling": "external",
        "org.gradle.jvm.version": 8,
        "org.gradle.libraryelements": "jar",
        "org.gradle.usage": "java-runtime"
      },
      "dependencies": [
        {
          "group": "com.google.code.gson",
          "module": "gson",
          "version": {
            "requires": "2.8.6"
          }
        }
      ],
      "files": [
        {
          "name": "shuriken-core-2.0.3.jar",
          "url": "shuriken-core-2.0.3.jar",
          "size": 288848,
          "sha512": "bcdca4ef37ab4e86b8c6da35382461b9f0ad57e2873af0515773398239728c5f80a877411e59f502cd56a42c4bc549fd4ef2fd2e1ad36a0f414cbe586f000379",
          "sha256": "5ab64e8d729e3a3f58d0ad6563913bf16ab677e81ff611722c1f6803d230a108",
          "sha1": "f536b337db5cb8a03e186726fc36b1245fec8eca",
          "md5": "d0d01715196b62e2e3efdabad2a1d1d1"
        }
      ]
    },
    {
      "name": "javadocElements",
      "attributes": {
        "org.gradle.category": "documentation",
        "org.gradle.dependency.bundling": "external",
        "org.gradle.docstype": "javadoc",
        "org.gradle.usage": "java-runtime"
      },
      "files": [
        {
          "name": "shuriken-core-2.0.3-javadoc.jar",
          "url": "shuriken-core-2.0.3-javadoc.jar",
          "size": 680598,
          "sha512": "7a6093746699b8cae3dc8094e9b8e70987fbb9ff8c7477ed572cf445feaa929218936a9191a947aeaadb2cdfc5aa099b2844df13efce624e8cebf07a1ae5b22e",
          "sha256": "c3263e3793448d585bdc1dd4a0308895850a61614644c50a45d7e959a0b7df92",
          "sha1": "4def02b1e26b0e828f8eae3da969d8326c559479",
          "md5": "c796a92b41df198e75eac6c98c2d01cb"
        }
      ]
    },
    {
      "name": "sourcesElements",
      "attributes": {
        "org.gradle.category": "documentation",
        "org.gradle.dependency.bundling": "external",
        "org.gradle.docstype": "sources",
        "org.gradle.usage": "java-runtime"
      },
      "files": [
        {
          "name": "shuriken-core-2.0.3-sources.jar",
          "url": "shuriken-core-2.0.3-sources.jar",
          "size": 184554,
          "sha512": "92f6d54f4c760075bdad7f3ffdcfd7b4e7b52750b60143db347568320543d834e6e42f182edd9bfae2914ceb453cac0070af29ef65f213f548f151c6e35c45df",
          "sha256": "d1a6bfd0e9d96ec4225a5266d463f707ab4a95db9f7cfe2d7f8f132a3f88c7fd",
          "sha1": "7aa98914e49609baf3a9c36ced6b37ef5374cc18",
          "md5": "835c97cdbafea641f8e8738962054321"
        }
      ]
    }
  ]
}
